{
  "name" : "CreateCsn",
  "method" : "POST",
  "uri" : "/v{version}/csn",
  "parameters" : [ {
    "name" : "version",
    "type" : "String",
    "required" : true,
    "position" : "URL",
    "default" : "1",
    "desc_key" : "common.version"
  }, {
    "name" : "clientToken",
    "type" : "String",
    "required" : false,
    "position" : "QUERY",
    "desc_key" : "csn.CreateCsn.clientToken"
  }, {
    "name" : "name",
    "type" : "String",
    "required" : true,
    "position" : "BODY",
    "desc_key" : "csn.CreateCsn.name"
  }, {
    "name" : "description",
    "type" : "String",
    "required" : false,
    "position" : "BODY",
    "desc_key" : "csn.CreateCsn.description"
  }, {
    "name" : "tags",
    "type" : "List",
    "required" : false,
    "position" : "BODY",
    "desc_key" : "csn.CreateCsn.tags",
    "sub_parameters" : [ {
      "name" : "tagKey",
      "type" : "String",
      "required" : false,
      "desc_key" : "csn.CreateCsn.tags.tagKey"
    }, {
      "name" : "tagValue",
      "type" : "String",
      "required" : false,
      "desc_key" : "csn.CreateCsn.tags.tagValue"
    } ]
  } ],
  "desc_key" : "csn.CreateCsn.desc"
}