{
  "name" : "ChangeSubUserPassword",
  "method" : "PUT",
  "uri" : "/v{version}/subUser/{userName}/update",
  "parameters" : [ {
    "name" : "version",
    "type" : "String",
    "required" : true,
    "position" : "URL",
    "default" : "1",
    "desc_key" : "common.version"
  }, {
    "name" : "userName",
    "type" : "String",
    "required" : true,
    "position" : "URL",
    "desc_key" : "iam.ChangeSubUserPassword.userName"
  }, {
    "name" : "password",
    "type" : "String",
    "required" : false,
    "position" : "BODY",
    "desc_key" : "iam.ChangeSubUserPassword.password"
  } ],
  "desc_key" : "iam.ChangeSubUserPassword.desc"
}